{
    "Tanah Tinggi": {
        "kemang": {
            "2025-09-16": 0.40000000000000213,
            "2025-09-17": 1.25,
            "2025-09-18": 0.5
        },
        "parung": {
            "2025-09-16": 0.40000000000000213,
            "2025-09-17": 1.125,
            "2025-09-18": 0.375
        },
        "tanjurhalang": {
            "2025-09-16": 0.40000000000000213,
            "2025-09-17": 1.25,
            "2025-09-18": 0.375
        }
    },
    "Tuban": {
        "baler_bale_agung": {
            "2025-09-16": 1.6000000000000014,
            "2025-09-17": 1.25,
            "2025-09-18": 0.625
        },
        "medewi": {
            "2025-09-16": 1.1999999999999993,
            "2025-09-17": 0.375,
            "2025-09-18": 0.75
        },
        "yehembang": {
            "2025-09-16": 2.0,
            "2025-09-17": 1.0,
            "2025-09-18": 1.5
        }
    }
}